canaryd/__init__.py
canaryd/__main__.py
canaryd/daemon.py
canaryd/diff.py
canaryd/exceptions.py
canaryd/log.py
canaryd/plugin.py
canaryd/remote.py
canaryd/script.py
canaryd/settings.py
canaryd/subprocess.py
canaryd/version.py
canaryd/ctl/__init__.py
canaryd/ctl/__main__.py
canaryd/ctl/check_root.py
canaryd/ctl/install_service.py
canaryd/ctl/scripts.py
canaryd/init_scripts/canaryd.conf
canaryd/init_scripts/canaryd.service
canaryd/init_scripts/canaryd.sh
canaryd/init_scripts/com.oxygem.canaryd.plist
canaryd/plugins/__init__.py
canaryd/plugins/containers.py
canaryd/plugins/containers_util.py
canaryd/plugins/hardware.py
canaryd/plugins/integrity.py
canaryd/plugins/iptables.py
canaryd/plugins/meta.py
canaryd/plugins/monitor.py
canaryd/plugins/monitor_util.py
canaryd/plugins/packages.py
canaryd/plugins/packages_util.py
canaryd/plugins/scripts.py
canaryd/plugins/services.py
canaryd/plugins/services_util.py
canaryd/plugins/sysctl.py
canaryd/plugins/users.py
canaryd/scripts/disk_health.py
canaryd/scripts/raid_health.py
canaryd-0.6.9.data/scripts/canaryctl
canaryd-0.6.9.data/scripts/canaryd
canaryd_packages/__init__.py
canaryd_packages/importlib.py
canaryd_packages/six.py
canaryd_packages/subprocess32.py
canaryd_packages/click/__init__.py
canaryd_packages/click/_bashcomplete.py
canaryd_packages/click/_compat.py
canaryd_packages/click/_termui_impl.py
canaryd_packages/click/_textwrap.py
canaryd_packages/click/_unicodefun.py
canaryd_packages/click/_winconsole.py
canaryd_packages/click/core.py
canaryd_packages/click/decorators.py
canaryd_packages/click/exceptions.py
canaryd_packages/click/formatting.py
canaryd_packages/click/globals.py
canaryd_packages/click/parser.py
canaryd_packages/click/termui.py
canaryd_packages/click/testing.py
canaryd_packages/click/types.py
canaryd_packages/click/utils.py
canaryd_packages/requests/__init__.py
canaryd_packages/requests/adapters.py
canaryd_packages/requests/api.py
canaryd_packages/requests/auth.py
canaryd_packages/requests/cacert.pem
canaryd-0.6.9.dist-info/LICENSE.md
canaryd-0.6.9.dist-info/METADATA
canaryd-0.6.9.dist-info/WHEEL
canaryd-0.6.9.dist-info/top_level.txt
canaryd-0.6.9.dist-info/RECORD
