Metadata-Version: 2.1
Name: canaryd
Version: 0.6.9
Summary: Client for Service Canary
Home-page: https://servicecanary.com
Author: Oxygem
Author-email: hello@oxygem.com
License: MIT
Platform: UNKNOWN
Provides-Extra: dev
Requires-Dist: nose (==1.3.7) ; extra == 'dev'
Requires-Dist: jsontest (==1.3) ; extra == 'dev'
Requires-Dist: coverage (==4.5.1) ; extra == 'dev'
Requires-Dist: mock (==1.3.0) ; extra == 'dev'
Requires-Dist: dictdiffer (==0.6.1) ; extra == 'dev'
Requires-Dist: wheel ; extra == 'dev'
Requires-Dist: twine (==1.11.0) ; extra == 'dev'
Requires-Dist: ipdb ; extra == 'dev'
Requires-Dist: ipdbplugin ; extra == 'dev'
Provides-Extra: test
Requires-Dist: nose (==1.3.7) ; extra == 'test'
Requires-Dist: jsontest (==1.3) ; extra == 'test'
Requires-Dist: coverage (==4.5.1) ; extra == 'test'
Requires-Dist: mock (==1.3.0) ; extra == 'test'
Requires-Dist: dictdiffer (==0.6.1) ; extra == 'test'
